pw_gen/__init__.py
pw_gen/pw_gen.py
pw_gen/pw_gen_utils.py
pw_gen/input_tables/alpha_chars.txt
pw_gen/input_tables/special_chars.txt
pw_gen/input_tables/types.txt
pw_gen/input_tables/unlegibles.txt
advanced_pw_gen-1.1.7.dist-info/LICENSE
advanced_pw_gen-1.1.7.dist-info/METADATA
advanced_pw_gen-1.1.7.dist-info/WHEEL
advanced_pw_gen-1.1.7.dist-info/top_level.txt
advanced_pw_gen-1.1.7.dist-info/RECORD
