Metadata-Version: 2.1
Name: advanced-pw-gen
Version: 1.1.7
Summary: An advanced password generator
Home-page: https://gitlab.com/darksidevt/pw_gen
Author: Arthur Edmiston
Author-email: arthur.edmiston@soledify.com
Maintainer: Arthur Edmiston
Maintainer-email: arthur.edmiston@soledify.com
License: MIT
Classifier: Programming Language :: Python :: 3
Classifier: Operating System :: OS Independent
License-File: LICENSE
Provides-Extra: dev
Requires-Dist: twine ; extra == 'dev'
Requires-Dist: wheel ; extra == 'dev'
Requires-Dist: pytest ; extra == 'dev'
